[
  {
    "name": "MenuProp",
    "value": {
      "name": "string",
      "icon": "any",
      "component": "any",
      "needsReport?": "boolean",
      "openedOnMobile?": "boolean"
    },
    "dependencies": [],
    "extends": []
  },
  {
    "name": "GenericContainerProps",
    "value": {
      "element?": "any",
      "xxxl?": "boolean",
      "xxl?": "boolean",
      "xl?": "boolean",
      "lg?": "boolean",
      "sm?": "boolean",
      "full?": "boolean",
      "horizontal?": "boolean",
      "vertical?": "boolean",
      "rounded?": "boolean",
      "colorless?": "boolean",
      "transparent?": "boolean",
      "primary?": "boolean",
      "secondary?": "boolean",
      "tertiary?": "boolean",
      "black?": "boolean",
      "red?": "boolean",
      "orange?": "boolean",
      "amber?": "boolean",
      "yellow?": "boolean",
      "lime?": "boolean",
      "green?": "boolean",
      "emerald?": "boolean",
      "teal?": "boolean",
      "cyan?": "boolean",
      "sky?": "boolean",
      "blue?": "boolean",
      "indigo?": "boolean",
      "violet?": "boolean",
      "purple?": "boolean",
      "fuchsia?": "boolean",
      "pink?": "boolean",
      "rose?": "boolean",
      "clickable?": "boolean",
      "focusable?": "boolean",
      "disabled?": "boolean",
      "svg?": "any",
      "leftSvg?": "any",
      "rightSvg?": "any",
      "src?": "string",
      "leftSrc?": "string",
      "rightSrc?": "string",
      "containerClasses?": "string",
      "illustrationClasses?": "string",
      "leftIllustrationClasses?": "string",
      "rightIllustrationClasses?": "string"
    },
    "dependencies": [],
    "extends": []
  },
  {
    "name": "GenericIllustrationProps",
    "value": {
      "right?": "boolean"
    },
    "dependencies": [],
    "extends": [
      "GenericContainerProps"
    ]
  },
  {
    "name": "Color",
    "value": "| 'black'   | 'white'   | 'gray'   | 'red'   | 'orange'   | 'amber'   | 'yellow'   | 'lime'   | 'green'   | 'emerald'   | 'teal'   | 'cyan'   | 'sky'   | 'blue'   | 'indigo'   | 'violet'   | 'purple'   | 'fuchsia'   | 'pink'   | 'rose'",
    "dependencies": [],
    "extends": []
  },
  {
    "name": "MathNumberObject",
    "value": {
      "[key: string]": "MathNumber | MathNumber[] | MathNumber[][]"
    },
    "dependencies": [
      "MathNumber"
    ],
    "extends": []
  },
  {
    "name": "ComputedData",
    "value": {
      "raw": "MathNumberObject",
      "parameters": "MathNumberObject",
      "computed": "MathNumberObject",
      "compute": "#40;#41; =#62; void"
    },
    "dependencies": [
      "MathNumberObject"
    ],
    "extends": []
  },
  {
    "name": "DataLabel",
    "value": {
      "name": "string",
      "unit": "MathUnit"
    },
    "dependencies": [
      "MathUnit"
    ],
    "extends": []
  },
  {
    "name": "DataValue",
    "value": {
      "label": "DataLabel",
      "value": "MathNumber | MathNumber[] | MathNumber[][]"
    },
    "dependencies": [
      "DataLabel",
      "MathNumber"
    ],
    "extends": []
  },
  {
    "name": "BaseDrop",
    "value": {
      "data": "ComputedData",
      "additionnalFields": "MachineField[]"
    },
    "dependencies": [
      "ComputedData",
      "MachineField"
    ],
    "extends": []
  },
  {
    "name": "JSONDrop",
    "value": {},
    "dependencies": [],
    "extends": []
  },
  {
    "name": "BaseField",
    "value": {
      "label": "string",
      "value": "| boolean     | number     | string     | SlidableNumber     | DateValue     | LongString     | SelectableString"
    },
    "dependencies": [
      "SlidableNumber",
      "DateValue",
      "LongString",
      "SelectableString"
    ],
    "extends": []
  },
  {
    "name": "JSONField",
    "value": {
      "label": "string",
      "value": "boolean | number | string"
    },
    "dependencies": [],
    "extends": []
  },
  {
    "name": "SlidableNumber",
    "value": {
      "kind": "'slidableNumber'",
      "value": "number",
      "step": "number",
      "min": "number",
      "max": "number"
    },
    "dependencies": [],
    "extends": []
  },
  {
    "name": "DateValue",
    "value": {
      "kind": "'date'",
      "value": "string"
    },
    "dependencies": [],
    "extends": []
  },
  {
    "name": "LongString",
    "value": {
      "kind": "'longString'",
      "value": "string"
    },
    "dependencies": [],
    "extends": []
  },
  {
    "name": "SelectableString",
    "value": {
      "kind": "'selectableString'",
      "value": "string",
      "possibleValues": "string[]",
      "strict": "boolean"
    },
    "dependencies": [],
    "extends": []
  },
  {
    "name": "HeavydynField",
    "value": {},
    "dependencies": [],
    "extends": [
      "BaseField"
    ]
  },
  {
    "name": "MaxidynField",
    "value": {},
    "dependencies": [],
    "extends": [
      "BaseField"
    ]
  },
  {
    "name": "MinidynField",
    "value": {},
    "dependencies": [],
    "extends": [
      "BaseField"
    ]
  },
  {
    "name": "MachineField",
    "value": "HeavydynField | MaxidynField | MinidynField",
    "dependencies": [
      "HeavydynField",
      "MaxidynField",
      "MinidynField"
    ],
    "extends": []
  },
  {
    "name": "Icon",
    "value": {
      "element": "HTMLElement",
      "color": "string",
      "setText": "#40;text: string#41; =#62; void",
      "setIcon": "#40;iconName: IconName#41; =#62; void"
    },
    "dependencies": [
      "HTMLElement"
    ],
    "extends": []
  },
  {
    "name": "IconName",
    "value": "| 'circle'   | 'triangle'   | 'square'   | 'rhombus'   | 'flare'   | 'pentagon'   | 'hexagon'   | 'hexagonAlt'   | 'heptagon'   | 'octagon'",
    "dependencies": [],
    "extends": []
  },
  {
    "name": "Image",
    "value": {
      "id": "string",
      "sourceData": "mapboxgl.ImageSourceRaw",
      "markerNW": "mapboxgl.Marker",
      "markerSE": "mapboxgl.Marker",
      "opacity": "number",
      "addToMap": "#40;isVisible: boolean#41; =#62; void",
      "remove": "#40;#41; =#62; void"
    },
    "dependencies": [
      "mapboxgl.ImageSourceRaw",
      "mapboxgl.Marker"
    ],
    "extends": []
  },
  {
    "name": "JSONImage",
    "value": {
      "name": "string",
      "opacity?": "number",
      "coordinates?": "#123;     nw: LngLat     se: LngLat   #125;"
    },
    "dependencies": [
      "LngLat"
    ],
    "extends": []
  },
  {
    "name": "ImageCoordinates",
    "value": {
      "tl": "XYCoord",
      "tr": "XYCoord",
      "bl": "XYCoord",
      "br": "XYCoord"
    },
    "dependencies": [
      "XYCoord"
    ],
    "extends": []
  },
  {
    "name": "Line",
    "value": {
      "addToMap": "#40;#41; =#62; void",
      "update": "#40;#41; =#62; void",
      "remove": "#40;#41; =#62; void"
    },
    "dependencies": [],
    "extends": []
  },
  {
    "name": "MathNumber",
    "value": {
      "value": "math.Unit | number",
      "unit": "MathUnit | string",
      "displayString": "string",
      "displayStringWithUnit": "string",
      "toDisplayedValue": "#40;#41; =#62; void"
    },
    "dependencies": [
      "math.Unit",
      "MathUnit"
    ],
    "extends": []
  },
  {
    "name": "MathUnit",
    "value": {
      "name": "string",
      "currentUnit": "string",
      "currentPrecision": "number",
      "possibleSettings": "[string, number][]",
      "possiblePrecisions": "number[]",
      "minDisplayedValue?": "number",
      "maxDisplayedValue?": "number",
      "thresholds?": "#123;     selected: PredefinedThreshold | CustomThreshold | null     list: PredefinedThreshold[]     // custom: CustomThreshold   #125;"
    },
    "dependencies": [
      "PredefinedThreshold",
      "CustomThreshold"
    ],
    "extends": []
  },
  {
    "name": "BasePoint",
    "value": {
      "machine": "MachineName",
      "number": "number",
      "marker": "mapboxgl.Marker",
      "icon": "Icon",
      "settings": "JSONPointSettings",
      "zone": "Zone | null",
      "data": "DataValue[]",
      "updateText": "#40;#41; =#62; void",
      "updateVisibility": "#40;#41; =#62; void",
      "addToMap": "#40;#41; =#62; void",
      "remove": "#40;#41; =#62; void"
    },
    "dependencies": [
      "MachineName",
      "mapboxgl.Marker",
      "Icon",
      "JSONPointSettings",
      "Zone",
      "DataValue"
    ],
    "extends": []
  },
  {
    "name": "BasePointCreatorParameters",
    "value": {
      "machine": "MachineName"
    },
    "dependencies": [
      "MachineName"
    ],
    "extends": [
      "MachinePointCreatorParameters"
    ]
  },
  {
    "name": "JSONPoint",
    "value": {
      "coordinates": "mapboxgl.LngLatLike",
      "settings": "JSONPointSettings",
      "informations": "JSONField[]",
      "drops": "JSONDrop[]"
    },
    "dependencies": [
      "mapboxgl.LngLatLike",
      "JSONPointSettings",
      "JSONField",
      "JSONDrop"
    ],
    "extends": []
  },
  {
    "name": "JSONPointSettings",
    "value": {
      "isVisible": "boolean"
    },
    "dependencies": [],
    "extends": []
  },
  {
    "name": "HeavydynPoint",
    "value": {
      "machine": "'heavydyn'"
    },
    "dependencies": [],
    "extends": [
      "BasePoint"
    ]
  },
  {
    "name": "MaxidynPoint",
    "value": {
      "machine": "'maxidyn'"
    },
    "dependencies": [],
    "extends": [
      "BasePoint"
    ]
  },
  {
    "name": "MinidynPoint",
    "value": {
      "machine": "'minidyn'"
    },
    "dependencies": [],
    "extends": [
      "BasePoint"
    ]
  },
  {
    "name": "MachinePoint",
    "value": "HeavydynPoint | MaxidynPoint | MinidynPoint",
    "dependencies": [
      "HeavydynPoint",
      "MaxidynPoint",
      "MinidynPoint"
    ],
    "extends": []
  },
  {
    "name": "PartialMachinePoint~MachinePoint~",
    "value": "PartialExtendedObject#60;   BasePoint,   MachinePoint #62;",
    "dependencies": [
      "PartialExtendedObject",
      "BasePoint",
      "MachinePoint"
    ],
    "extends": []
  },
  {
    "name": "MachinePointCreatorParameters",
    "value": {
      "number": "number",
      "iconName": "IconName",
      "projectSettings": "JSONProjectSettings",
      "reportSettings": "JSONReportSettings"
    },
    "dependencies": [
      "IconName",
      "JSONProjectSettings",
      "JSONReportSettings"
    ],
    "extends": []
  },
  {
    "name": "BaseProject",
    "value": {
      "machine": "MachineName",
      "name": "MachineField",
      "informations": "MachineField[]",
      "reports": "SelectableList#60;MachineReport#62;",
      "units": "MachineUnits",
      "settings": "JSONProjectSettings",
      "images": "Image[]",
      "refreshLinesAndImages": "#40;#41; =#62; void",
      "setMapStyle": "#40;styleIndex: number#41; =#62; void",
      "fitOnMap": "#40;#41; =#62; void",
      "addToMap": "#40;#41; =#62; void",
      "remove": "#40;#41; =#62; void"
    },
    "dependencies": [
      "MachineName",
      "MachineField",
      "SelectableList",
      "MachineReport",
      "MachineUnits",
      "JSONProjectSettings",
      "Image"
    ],
    "extends": []
  },
  {
    "name": "BaseProjectCreatorParameters",
    "value": {
      "machine": "MachineName",
      "units": "MachineUnits"
    },
    "dependencies": [
      "MachineName",
      "MachineUnits"
    ],
    "extends": []
  },
  {
    "name": "JSONProject",
    "value": {
      "name": "string",
      "machine": "MachineName",
      "selectedReport?": "number",
      "settings": "JSONProjectSettings",
      "images": "JSONImage[]",
      "informations": "JSONField[]",
      "reports": "JSONReport[]",
      "units": "JSONUnits"
    },
    "dependencies": [
      "MachineName",
      "JSONProjectSettings",
      "JSONImage",
      "JSONField",
      "JSONReport",
      "JSONUnits"
    ],
    "extends": []
  },
  {
    "name": "MachineName",
    "value": "'heavydyn' | 'maxidyn' | 'minidyn'",
    "dependencies": [],
    "extends": []
  },
  {
    "name": "JSONProjectSettings",
    "value": {
      "arePointsVisible": "boolean",
      "arePointsLinked": "boolean",
      "arePointsLocked": "boolean",
      "areImagesVisible": "boolean",
      "pointsState": "PointsState",
      "map": "#123;     styleIndex: number     coordinates?: LngLat     zoom?: number   #125;"
    },
    "dependencies": [
      "PointsState",
      "LngLat"
    ],
    "extends": []
  },
  {
    "name": "PointsState",
    "value": "'value' | 'number' | 'nothing'",
    "dependencies": [],
    "extends": []
  },
  {
    "name": "HeavydynProject",
    "value": {
      "machine": "'heavydyn'",
      "reports": "SelectableList#60;HeavydynReport#62;"
    },
    "dependencies": [
      "SelectableList",
      "HeavydynReport"
    ],
    "extends": [
      "BaseProject"
    ]
  },
  {
    "name": "HeavydynUnits",
    "value": {
      "deformation": "MathUnit",
      "force": "MathUnit",
      "temperature": "MathUnit"
    },
    "dependencies": [
      "MathUnit"
    ],
    "extends": []
  },
  {
    "name": "JSONHeavydynUnits",
    "value": {
      "deformation": "'mm' | '1/100 mm' | 'um'",
      "force": "'N' | 'kN' | 'lbs'",
      "temperature": "'degC' | 'degF' | 'K'"
    },
    "dependencies": [],
    "extends": []
  },
  {
    "name": "MaxidynProject",
    "value": {
      "machine": "'maxidyn'",
      "reports": "SelectableList#60;MaxidynReport#62;"
    },
    "dependencies": [
      "SelectableList",
      "MaxidynReport"
    ],
    "extends": [
      "BaseProject"
    ]
  },
  {
    "name": "MaxidynUnits",
    "value": {
      "modulus": "MathUnit",
      "deformation": "MathUnit",
      "force": "MathUnit"
    },
    "dependencies": [
      "MathUnit"
    ],
    "extends": []
  },
  {
    "name": "JSONMaxidynUnits",
    "value": {
      "modulus": "'MPa' | 'kN'",
      "deformation": "'mm' | 'um'",
      "force": "'N' | 'kN'"
    },
    "dependencies": [],
    "extends": []
  },
  {
    "name": "MinidynProject",
    "value": {
      "machine": "'minidyn'",
      "reports": "SelectableList#60;MinidynReport#62;"
    },
    "dependencies": [
      "SelectableList",
      "MinidynReport"
    ],
    "extends": [
      "BaseProject"
    ]
  },
  {
    "name": "MinidynUnits",
    "value": {
      "modulus": "MathUnit",
      "deformation": "MathUnit",
      "force": "MathUnit",
      "temperature": "MathUnit"
    },
    "dependencies": [
      "MathUnit"
    ],
    "extends": []
  },
  {
    "name": "JSONMinidynUnits",
    "value": {
      "modulus": "'MPa' | 'kN'",
      "deformation": "'mm' | 'um'",
      "force": "'N' | 'kN'"
    },
    "dependencies": [],
    "extends": []
  },
  {
    "name": "MachineProject",
    "value": "HeavydynProject | MaxidynProject | MinidynProject",
    "dependencies": [
      "HeavydynProject",
      "MaxidynProject",
      "MinidynProject"
    ],
    "extends": []
  },
  {
    "name": "PartialMachineProject~MachineProject~",
    "value": "PartialExtendedObject#60;   BaseProject,   MachineProject #62;",
    "dependencies": [
      "PartialExtendedObject",
      "BaseProject",
      "MachineProject"
    ],
    "extends": []
  },
  {
    "name": "JSONUnits",
    "value": "JSONHeavydynUnits | JSONMaxidynUnits | JSONMinidynUnits",
    "dependencies": [
      "JSONHeavydynUnits",
      "JSONMaxidynUnits",
      "JSONMinidynUnits"
    ],
    "extends": []
  },
  {
    "name": "MachineUnits",
    "value": "HeavydynUnits | MaxidynUnits | MinidynUnits",
    "dependencies": [
      "HeavydynUnits",
      "MaxidynUnits",
      "MinidynUnits"
    ],
    "extends": []
  },
  {
    "name": "BaseReport",
    "value": {
      "machine": "MachineName",
      "name": "MachineField",
      "points": "MachinePoint[]",
      "line": "Line",
      "zones": "Zone[]",
      "screenshots": "string[]",
      "dataLabels": "ReportDataLabels",
      "settings": "JSONReportSettings",
      "platform": "MachineField[]",
      "informations": "MachineField[]",
      "isOnMap": "boolean",
      "fitOnMap": "#40;#41; =#62; void",
      "addToMap": "#40;#41; =#62; void",
      "remove": "#40;#41; =#62; void"
    },
    "dependencies": [
      "MachineName",
      "MachineField",
      "MachinePoint",
      "Line",
      "Zone",
      "ReportDataLabels",
      "JSONReportSettings"
    ],
    "extends": []
  },
  {
    "name": "ReportDataLabels",
    "value": {
      "groups": "SelectableList#60;GroupedDataLabels#62;",
      "table": "SelectableList#60;TableDataLabelsParameters#62;"
    },
    "dependencies": [
      "SelectableList",
      "GroupedDataLabels",
      "TableDataLabelsParameters"
    ],
    "extends": []
  },
  {
    "name": "GroupedDataLabels",
    "value": {
      "from": "DataLabelsFrom",
      "choices": "SelectableList#60;DataLabel#62;",
      "indexes?": "SelectableList#60;MachineDropIndex#62;"
    },
    "dependencies": [
      "DataLabelsFrom",
      "SelectableList",
      "DataLabel",
      "MachineDropIndex"
    ],
    "extends": []
  },
  {
    "name": "TableDataLabelsParameters",
    "value": {
      "group": "GroupedDataLabels",
      "index?": "MachineDropIndex",
      "dataLabels": "DataLabel[]"
    },
    "dependencies": [
      "GroupedDataLabels",
      "MachineDropIndex",
      "DataLabel"
    ],
    "extends": []
  },
  {
    "name": "BaseReportCreatorParameters",
    "value": {
      "machine": "MachineName",
      "groupedDataLabels": "SelectableList#60;GroupedDataLabels#62;"
    },
    "dependencies": [
      "MachineName",
      "SelectableList",
      "GroupedDataLabels"
    ],
    "extends": [
      "MachineReportCreatorParameters"
    ]
  },
  {
    "name": "JSONReport",
    "value": {
      "name": "string",
      "points": "JSONPoint[]",
      "dataLabels": "JSONReportDataLabels",
      "zones": "JSONZone[]",
      "settings": "JSONReportSettings",
      "screenshots": "number[]",
      "platform": "JSONField[]",
      "informations": "JSONField[]"
    },
    "dependencies": [
      "JSONPoint",
      "JSONReportDataLabels",
      "JSONZone",
      "JSONReportSettings",
      "JSONField"
    ],
    "extends": []
  },
  {
    "name": "JSONReportDataLabels",
    "value": {
      "groups": "SelectableList#60;number, JSONGroupedDataLabels#62;",
      "table": "SelectableList#60;number, JSONTableDataLabelsParameters#62;"
    },
    "dependencies": [
      "SelectableList",
      "JSONGroupedDataLabels",
      "JSONTableDataLabelsParameters"
    ],
    "extends": []
  },
  {
    "name": "JSONGroupedDataLabels",
    "value": {
      "from": "DataLabelsFrom",
      "choices": "SelectableOptionalList#60;number, string#62;",
      "indexes?": "SelectableList#60;number, MachineDropIndex#62;"
    },
    "dependencies": [
      "DataLabelsFrom",
      "SelectableOptionalList",
      "SelectableList",
      "MachineDropIndex"
    ],
    "extends": []
  },
  {
    "name": "JSONTableDataLabelsParameters",
    "value": {
      "from": "DataLabelsFrom",
      "index?": "number",
      "dataLabels": "string[]"
    },
    "dependencies": [
      "DataLabelsFrom"
    ],
    "extends": []
  },
  {
    "name": "DataLabelsFrom",
    "value": "'Drop' | 'Test' | 'Zone'",
    "dependencies": [],
    "extends": []
  },
  {
    "name": "JSONReportSettings",
    "value": {
      "iconName": "IconName",
      "isVisible": "boolean",
      "selectedColorization": "'Threshold' | 'Zone'",
      "threshold": "#123;     colors: ThresholdColors     custom: #123;#125;   #125;"
    },
    "dependencies": [
      "IconName",
      "ThresholdColors"
    ],
    "extends": []
  },
  {
    "name": "ThresholdColors",
    "value": {
      "low": "Color",
      "middle": "Color",
      "high": "Color"
    },
    "dependencies": [
      "Color"
    ],
    "extends": []
  },
  {
    "name": "BaseDropIndex",
    "value": {
      "machine": "MachineName",
      "type": "string",
      "displayedIndex": "number"
    },
    "dependencies": [
      "MachineName"
    ],
    "extends": []
  },
  {
    "name": "HeavydynReport",
    "value": {
      "machine": "'heavydyn'",
      "points": "HeavydynPoint[]",
      "platform": "HeavydynField[]",
      "informations": "HeavydynField[]"
    },
    "dependencies": [
      "HeavydynPoint",
      "HeavydynField"
    ],
    "extends": [
      "BaseReport"
    ]
  },
  {
    "name": "HeavydynReportCreatorParameters",
    "value": {
      "units": "HeavydynUnits"
    },
    "dependencies": [
      "HeavydynUnits"
    ],
    "extends": [
      "MachineReportCreatorParameters"
    ]
  },
  {
    "name": "HeavydynDropType",
    "value": "'Distance' | 'Force' | 'Time'",
    "dependencies": [],
    "extends": []
  },
  {
    "name": "HeavydynDropIndex",
    "value": {
      "machine": "'heavydyn'",
      "type": "HeavydynDropType",
      "value": "MathNumber"
    },
    "dependencies": [
      "HeavydynDropType",
      "MathNumber"
    ],
    "extends": [
      "BaseDropIndex"
    ]
  },
  {
    "name": "JSONHeavydynDropIndex",
    "value": {
      "machine": "'heavydyn'",
      "type": "HeavydynDropType",
      "value": "number"
    },
    "dependencies": [
      "HeavydynDropType"
    ],
    "extends": [
      "BaseDropIndex"
    ]
  },
  {
    "name": "MaxidynReport",
    "value": {
      "machine": "'maxidyn'",
      "points": "MaxidynPoint[]",
      "platform": "MaxidynField[]",
      "informations": "MaxidynField[]"
    },
    "dependencies": [
      "MaxidynPoint",
      "MaxidynField"
    ],
    "extends": [
      "BaseReport"
    ]
  },
  {
    "name": "MaxidynReportCreatorParameters",
    "value": {
      "units": "MaxidynUnits"
    },
    "dependencies": [
      "MaxidynUnits"
    ],
    "extends": [
      "MachineReportCreatorParameters"
    ]
  },
  {
    "name": "MaxidynDropType",
    "value": "'Training' | 'Averaging'",
    "dependencies": [],
    "extends": []
  },
  {
    "name": "MaxidynDropIndex",
    "value": {
      "machine": "'maxidyn'",
      "type": "MaxidynDropType"
    },
    "dependencies": [
      "MaxidynDropType"
    ],
    "extends": [
      "BaseDropIndex"
    ]
  },
  {
    "name": "MinidynReport",
    "value": {
      "machine": "'minidyn'",
      "points": "MinidynPoint[]",
      "platform": "MinidynField[]",
      "informations": "MinidynField[]"
    },
    "dependencies": [
      "MinidynPoint",
      "MinidynField"
    ],
    "extends": [
      "BaseReport"
    ]
  },
  {
    "name": "MinidynReportCreatorParameters",
    "value": {
      "units": "MinidynUnits"
    },
    "dependencies": [
      "MinidynUnits"
    ],
    "extends": [
      "MachineReportCreatorParameters"
    ]
  },
  {
    "name": "MinidynDropType",
    "value": "'Training' | 'Averaging'",
    "dependencies": [],
    "extends": []
  },
  {
    "name": "MinidynDropIndex",
    "value": {
      "machine": "'minidyn'",
      "type": "MinidynDropType"
    },
    "dependencies": [
      "MinidynDropType"
    ],
    "extends": [
      "BaseDropIndex"
    ]
  },
  {
    "name": "MachineReport",
    "value": "HeavydynReport | MaxidynReport | MinidynReport",
    "dependencies": [
      "HeavydynReport",
      "MaxidynReport",
      "MinidynReport"
    ],
    "extends": []
  },
  {
    "name": "PartialMachineReport~MachineReport~",
    "value": "PartialExtendedObject#60;   BaseReport,   MachineReport #62;",
    "dependencies": [
      "PartialExtendedObject",
      "BaseReport",
      "MachineReport"
    ],
    "extends": []
  },
  {
    "name": "MachineReportCreatorParameters",
    "value": {
      "projectSettings": "JSONProjectSettings",
      "units": "MachineUnits"
    },
    "dependencies": [
      "JSONProjectSettings",
      "MachineUnits"
    ],
    "extends": []
  },
  {
    "name": "MachineDropIndex",
    "value": "HeavydynDropIndex | MaxidynDropIndex | MinidynDropIndex",
    "dependencies": [
      "HeavydynDropIndex",
      "MaxidynDropIndex",
      "MinidynDropIndex"
    ],
    "extends": []
  },
  {
    "name": "JSONMachineDropIndex",
    "value": "| JSONHeavydynDropIndex   | MaxidynDropIndex   | MinidynDropIndex",
    "dependencies": [
      "JSONHeavydynDropIndex",
      "MaxidynDropIndex",
      "MinidynDropIndex"
    ],
    "extends": []
  },
  {
    "name": "CustomThreshold",
    "value": {
      "name": "string",
      "value": "number"
    },
    "dependencies": [],
    "extends": []
  },
  {
    "name": "PredefinedThreshold",
    "value": {
      "name": "string",
      "value": "number"
    },
    "dependencies": [],
    "extends": []
  },
  {
    "name": "PartialExtendedObject~BaseObject, MachineObject~",
    "value": "Required#60;BaseObject#62; &   Partial#60;Omit#60;MachineObject, keyof BaseObject#62;#62;",
    "dependencies": [
      "Required",
      "BaseObject",
      "Partial",
      "Omit",
      "MachineObject"
    ],
    "extends": []
  },
  {
    "name": "WatcherHandler",
    "value": {
      "add": "#40;stop: #40;#41; =#62; void#41; =#62; void",
      "remove": "#40;stop: #40;#41; =#62; void#41; =#62; void",
      "clean": "#40;#41; =#62; void"
    },
    "dependencies": [],
    "extends": []
  },
  {
    "name": "Zone",
    "value": {
      "name": "string",
      "color": "Color"
    },
    "dependencies": [
      "Color"
    ],
    "extends": []
  },
  {
    "name": "JSONZone",
    "value": {
      "name": "string",
      "color?": "Color"
    },
    "dependencies": [
      "Color"
    ],
    "extends": []
  },
  {
    "name": "LngLat",
    "value": {
      "lng": "number",
      "lat": "number"
    },
    "dependencies": [],
    "extends": []
  },
  {
    "name": "XYCoord",
    "value": {
      "x": "number",
      "y": "number"
    },
    "dependencies": [],
    "extends": []
  },
  {
    "name": "SelectableList~S, L~",
    "value": {
      "selected": "S | null",
      "list": "L[]"
    },
    "dependencies": [
      "S",
      "L"
    ],
    "extends": []
  },
  {
    "name": "SelectableOptionalList~S, L~",
    "value": {
      "selected": "S | null",
      "list?": "L[]"
    },
    "dependencies": [
      "S",
      "L"
    ],
    "extends": []
  },
  {
    "name": "DeepRequired~T~",
    "value": "#123;   [K in keyof T]: Required#60;DeepRequired#60;T[K]#62;#62; #125;",
    "dependencies": [
      "T",
      "Required",
      "DeepRequired",
      "K"
    ],
    "extends": []
  },
  {
    "name": "Store",
    "value": {
      "projects": "SelectableList#60;MachineProject#62;",
      "map": "mapboxgl.Map | null",
      "save": "#40;key: StoreKeys, value: StoreSaveableTypes#41; =#62; void"
    },
    "dependencies": [
      "SelectableList",
      "MachineProject",
      "mapboxgl.Map"
    ],
    "extends": []
  },
  {
    "name": "StoreKeys",
    "value": "Exclude#60;keyof Store, 'save'#62;",
    "dependencies": [
      "Exclude",
      "Store"
    ],
    "extends": []
  },
  {
    "name": "StoreTypes",
    "value": "Store[keyof Store]",
    "dependencies": [
      "Store"
    ],
    "extends": []
  },
  {
    "name": "StoreSaveableTypes",
    "value": "Extract#60;   StoreTypes,   string[] | number[] | boolean[] | string | number | boolean | null #62;",
    "dependencies": [
      "Extract",
      "StoreTypes"
    ],
    "extends": []
  }
]